splent_cli/__init__.py
splent_cli/__main__.py
splent_cli/cli.py
splent_cli/commands/__init__.py
splent_cli/commands/clear_cache.py
splent_cli/commands/clear_log.py
splent_cli/commands/clear_uploads.py
splent_cli/commands/compose_env.py
splent_cli/commands/coverage.py
splent_cli/commands/db_console.py
splent_cli/commands/db_dump.py
splent_cli/commands/db_migrate.py
splent_cli/commands/db_reset.py
splent_cli/commands/db_seed.py
splent_cli/commands/env.py
splent_cli/commands/feature_create.py
splent_cli/commands/feature_list.py
splent_cli/commands/info.py
splent_cli/commands/linter.py
splent_cli/commands/locust.py
splent_cli/commands/product_create.py
splent_cli/commands/route_list.py
splent_cli/commands/selenium.py
splent_cli/commands/test.py
splent_cli/commands/webpack_compile.py
splent_cli/utils/__init__.py
splent_cli/utils/dynamic_imports.py
splent_cli/utils/feature_installer.py
splent_cli/utils/feature_utils.py
splent_cli/utils/path_utils.py
splent_cli-0.0.3.dist-info/licenses/LICENSE
splent_cli-0.0.3.dist-info/METADATA
splent_cli-0.0.3.dist-info/WHEEL
splent_cli-0.0.3.dist-info/entry_points.txt
splent_cli-0.0.3.dist-info/top_level.txt
splent_cli-0.0.3.dist-info/RECORD
